crgb.py
crgb-1.0.2.dist-info/METADATA
crgb-1.0.2.dist-info/WHEEL
crgb-1.0.2.dist-info/RECORD
